usr_local_pull/__init__.py
usr_local_pull/app.py
usr_local_pull/archive_extractor.py
usr_local_pull/cli.py
usr_local_pull/gh_client.py
usr_local_pull/supported_apps/__init__.py
usr_local_pull/supported_apps/bat.py
usr_local_pull/supported_apps/dasel.py
usr_local_pull/supported_apps/eza.py
usr_local_pull/supported_apps/fd_find.py
usr_local_pull/supported_apps/fzf.py
usr_local_pull/supported_apps/gojq.py
usr_local_pull/supported_apps/jid.py
usr_local_pull/supported_apps/jq.py
usr_local_pull/supported_apps/jqp.py
usr_local_pull/supported_apps/lazygit.py
usr_local_pull/supported_apps/mdbook.py
usr_local_pull/supported_apps/neovide.py
usr_local_pull/supported_apps/ripgrep.py
usr_local_pull/supported_apps/starship.py
usr_local_pull/supported_apps/stylua.py
usr_local_pull/supported_apps/xq.py
usr_local_pull/supported_apps/yq.py
usr_local_pull-0.2.0.dist-info/METADATA
usr_local_pull-0.2.0.dist-info/WHEEL
usr_local_pull-0.2.0.dist-info/entry_points.txt
usr_local_pull-0.2.0.dist-info/top_level.txt
usr_local_pull-0.2.0.dist-info/RECORD
