Metadata-Version: 2.1
Name: usr-local-pull
Version: 0.2.0
Summary: Installs popular cmdline utils into /usr/local directly from GitHub released artifacts.
Author-email: Tomislav Adamic <tomislav.adamic@tellus.hr>
Project-URL: Source, https://github.com/tadams42/usr-local-pull
Keywords: commandline cli packaging
Platform: any
Classifier: Development Status :: 5 - Production/Stable
Classifier: Intended Audience :: Developers
Classifier: Topic :: Software Development :: Build Tools
Classifier: License :: OSI Approved :: MIT License
Classifier: Operating System :: POSIX :: Linux
Classifier: Programming Language :: Python
Classifier: Programming Language :: Python :: 3
Classifier: Programming Language :: Python :: 3.10
Classifier: Programming Language :: Python :: 3.11
Classifier: Programming Language :: Python :: 3.12
Classifier: Programming Language :: Python :: 3.13
Classifier: Programming Language :: Python :: 3 :: Only
Requires-Python: >=3.10
Requires-Dist: packaging>=24.1
Requires-Dist: click==8.1.7
Requires-Dist: ar>=1.0.0
Provides-Extra: dev
Requires-Dist: ipython; extra == "dev"
Requires-Dist: black; extra == "dev"
Requires-Dist: ruff; extra == "dev"
Requires-Dist: check-manifest; extra == "dev"
Requires-Dist: rich; extra == "dev"
Provides-Extra: tests
Requires-Dist: pytest; extra == "tests"
Requires-Dist: pytest-spec; extra == "tests"
